{
  "title":"15-511su04.jpg",
  "description": "",
  "file": "/courses/15-511-financial-accounting-summer-2004/f89e7ab180350867739e28c2282599c0_15-511su04.jpg",
  "learning_resource_types": [],
  "resource_type": "Image",
  "file_type": "image/jpeg",
  "image_metadata": {"caption":"This diagram explains the necessity of financial accounting: it promotes the exchange of resources. (Diagram by Prof. S. P. Kothari. Background photograph courtesy of OCW.)","credit":"","image-alt":"Diagram showing how information flows from a company to outsiders."}}
